pybel_cx/__init__.py
pybel_cx/__main__.py
pybel_cx/cli.py
pybel_cx/constants.py
pybel_cx/cx.py
pybel_cx/ndex_utils.py
pybel_cx/utils.py
pybel_cx-0.1.3.dist-info/LICENSE
pybel_cx-0.1.3.dist-info/METADATA
pybel_cx-0.1.3.dist-info/WHEEL
pybel_cx-0.1.3.dist-info/entry_points.txt
pybel_cx-0.1.3.dist-info/top_level.txt
pybel_cx-0.1.3.dist-info/RECORD
