Metadata-Version: 2.1
Name: pybel-cx
Version: 0.1.3
Summary: A PyBEL extension for interconversion with CX
Home-page: https://github.com/pybel/pybel-cx
Author: Charles Tapley Hoyt
Author-email: cthoyt@gmail.com
Maintainer: Charles Tapley Hoyt
Maintainer-email: cthoyt@gmail.com
License: MIT
Download-URL: https://github.com/pybel/pybel-cx/releases
Project-URL: Bug Tracker, https://github.com/pybel/pybel-cx/issues
Project-URL: Source Code, https://github.com/pybel/pybel-cx
Project-URL: Documentation, https://pybel.readthedocs.io
Keywords: Biological Expression Language,BEL,Domain Specific Language,DSL,Systems Biology,Networks Biology,NDEx
Platform: UNKNOWN
Classifier: Development Status :: 4 - Beta
Classifier: Environment :: Console
Classifier: Intended Audience :: Developers
Classifier: Intended Audience :: Science/Research
Classifier: License :: OSI Approved :: MIT License
Classifier: Operating System :: OS Independent
Classifier: Programming Language :: Python
Classifier: Programming Language :: Python :: 3.7
Classifier: Programming Language :: Python :: 3.6
Classifier: Programming Language :: Python :: 3 :: Only
Classifier: Topic :: Scientific/Engineering :: Bio-Informatics
Classifier: Topic :: Scientific/Engineering :: Chemistry
Requires-Python: >=3.6
Requires-Dist: pybel (>=0.13.0<0.14.0)
Requires-Dist: ndex2
Requires-Dist: requests
Requires-Dist: click
Provides-Extra: docs
Requires-Dist: sphinx ; extra == 'docs'
Requires-Dist: sphinx-rtd-theme ; extra == 'docs'
Requires-Dist: sphinx-click ; extra == 'docs'
Requires-Dist: sphinx-autodoc-typehints ; extra == 'docs'
